blender_wormholes/__init__.py
blender_wormholes/constants.py
blender_wormholes/constraints.py
blender_wormholes/core.py
blender_wormholes/utility.py
blender_wormholes-0.0.2.dist-info/METADATA
blender_wormholes-0.0.2.dist-info/WHEEL
blender_wormholes-0.0.2.dist-info/entry_points.txt
blender_wormholes-0.0.2.dist-info/top_level.txt
blender_wormholes-0.0.2.dist-info/RECORD
