Metadata-Version: 2.1
Name: blender-wormholes
Version: 0.0.2
Summary: helper library
Home-page: https://github.com/coreqode/blender_wormholes
Author: Chandradeep Pokhariya
Author-email: cdpokhariya@gmail.com
License: MIT
Classifier: Programming Language :: Python :: 3
Classifier: License :: OSI Approved :: MIT License
Classifier: Operating System :: OS Independent
